azcam_mag/__init__.py
azcam_mag/camera_server.py
azcam_mag/controller_mag.py
azcam_mag/exposure_mag.py
azcam_mag/receive_data.py
azcam_mag/tempcon_mag.py
azcam_mag/udpinterface.py
azcam_mag-22.3.2.dist-info/LICENSE
azcam_mag-22.3.2.dist-info/WHEEL
azcam_mag-22.3.2.dist-info/METADATA
azcam_mag-22.3.2.dist-info/RECORD
